easyq/__init__.py
easyq/authentication.py
easyq/client.py
easyq/configuration.py
easyq/logging.py
easyq/queuemanager.py
easyq/server.py
easyq/cli/__init__.py
easyq/cli/argcompletion.py
easyq/cli/base.py
easyq/cli/main.py
easyq/cli/server.py
easyq-0.1.0a1.dist-info/METADATA
easyq-0.1.0a1.dist-info/RECORD
easyq-0.1.0a1.dist-info/WHEEL
easyq-0.1.0a1.dist-info/entry_points.txt
easyq-0.1.0a1.dist-info/top_level.txt
